retrophase/__init__.py
retrophase/retro.py
retrophase-0.14.dist-info/licenses/LICENSE
retrophase-0.14.dist-info/METADATA
retrophase-0.14.dist-info/WHEEL
retrophase-0.14.dist-info/entry_points.txt
retrophase-0.14.dist-info/top_level.txt
retrophase-0.14.dist-info/RECORD
